<?xml version="1.0" encoding="utf-8"?>
<databaseChangeLog
    xmlns="http://www.liquibase.org/xml/ns/dbchangelog"
    xmlns:ext="http://www.liquibase.org/xml/ns/dbchangelog-ext"
    xmlns:xsi="http://www.w3.org/2001/XMLSchema-instance"
    xsi:schemaLocation="http://www.liquibase.org/xml/ns/dbchangelog http://www.liquibase.org/xml/ns/dbchangelog/dbchangelog-3.5.xsd
                        http://www.liquibase.org/xml/ns/dbchangelog-ext http://www.liquibase.org/xml/ns/dbchangelog/dbchangelog-ext.xsd">

    <changeSet id="12312312421421" author="jhipster">
        <loadData file="config/liquibase/faculties.csv"
                  separator=";"
                  tableName="faculty">
        </loadData>

        <loadData file="config/liquibase/departments.csv"
                  separator=";"
                  tableName="department">
        </loadData>

        <loadData file="config/liquibase/programmes.csv"
                  separator=";"
                  tableName="programme">
        </loadData>

        <loadData file="config/liquibase/programme_props.csv"
                  separator=";"
                  tableName="programme_prop">
        </loadData>
    </changeSet>
    <!-- jhipster-needle-liquibase-add-changeset - JHipster will add changesets here, do not remove-->
</databaseChangeLog>
